lmdemo/__init__.py
lmdemo/__main__.py
lmdemo/linmodest.py
lmdemo-1.1.0.dist-info/entry_points.txt
lmdemo-1.1.0.dist-info/WHEEL
lmdemo-1.1.0.dist-info/METADATA
lmdemo-1.1.0.dist-info/RECORD
